whos_there/__about__.py
whos_there/__init__.py
whos_there/callback.py
whos_there/cli.py
whos_there/py.typed
whos_there/senders/__init__.py
whos_there/senders/base.py
whos_there/senders/debug.py
whos_there/senders/discord.py
whos_there/senders/email.py
whos_there/senders/slack.py
whos_there/senders/teams.py
whos_there/senders/telegram.py
whos_there/utils/logging.py
whos_there-0.4.1.dist-info/LICENSE
whos_there-0.4.1.dist-info/METADATA
whos_there-0.4.1.dist-info/WHEEL
whos_there-0.4.1.dist-info/entry_points.txt
whos_there-0.4.1.dist-info/RECORD
