Metadata-Version: 2.1
Name: whos-there
Version: 0.4.1
Summary: The spiritual successor to knockknock for PyTorch Lightning, get notified when your training ends
Home-page: https://twsl.github.io/whos-there/
License: MIT
Keywords: python,pytorch,pytorch-lightning,machine-learning,deep-learning
Author: twsl
Author-email: 45483159+twsl@users.noreply.github.com
Maintainer: twsl
Maintainer-email: 45483159+twsl@users.noreply.github.com
Requires-Python: >=3.10,<4.0
Classifier: License :: OSI Approved :: MIT License
Classifier: Programming Language :: Python :: 3
Classifier: Programming Language :: Python :: 3.10
Classifier: Programming Language :: Python :: 3.11
Classifier: Programming Language :: Python :: 3.12
Classifier: Programming Language :: Python :: 3.13
Classifier: Topic :: Software Development
Requires-Dist: lightning (>=2.4.0,<3.0.0)
Requires-Dist: python-telegram-bot (>=21.8,<22.0)
Requires-Dist: requests (>=2.32.3,<3.0.0)
Project-URL: Repository, https://github.com/twsl/whos-there
Project-URL: issues, https://github.com/twsl/whos-there/issues
